YAML2ST.py
YAML2ST-1.0.22.dist-info/LICENSE.txt
YAML2ST-1.0.22.dist-info/METADATA
YAML2ST-1.0.22.dist-info/WHEEL
YAML2ST-1.0.22.dist-info/top_level.txt
YAML2ST-1.0.22.dist-info/RECORD
