Metadata-Version: 2.1
Name: YAML2ST
Version: 1.0.22
Summary: YAML2ST automates streamlit input widgets from a YAML.
Home-page: https://github.com/singingwithcode/YAML2ST
Author: Matthew Klich, Kelly Anderson
Author-email: m@matthewklich.com
Classifier: Programming Language :: Python :: 3
Classifier: License :: OSI Approved :: MIT License
Classifier: Operating System :: OS Independent
License-File: LICENSE.txt
Requires-Dist: PyYAML
